LICENSE
MANIFEST.in
README.rst
requirements.txt
setup.cfg
setup.py
HabitatOS/__init__.py
HabitatOS/manage.py
HabitatOS.egg-info/PKG-INFO
HabitatOS.egg-info/SOURCES.txt
HabitatOS.egg-info/dependency_links.txt
HabitatOS.egg-info/entry_points.txt
HabitatOS.egg-info/requires.txt
HabitatOS.egg-info/top_level.txt
HabitatOS/bin/sensor-zwave-collector.py
HabitatOS/bin/sensor-zwave-uploader.py
HabitatOS/client/__init__.py
HabitatOS/client/basic.py
HabitatOS/client/config.json
HabitatOS/client/oauth.py
HabitatOS/habitat/.DS_Store
HabitatOS/habitat/__init__.py
HabitatOS/habitat/settings.py
HabitatOS/habitat/tests.py
HabitatOS/habitat/urls.py
HabitatOS/habitat/wsgi.py
HabitatOS/habitat/_common/__init__.py
HabitatOS/habitat/_common/admin.py
HabitatOS/habitat/_common/fixtures/auth_group.json
HabitatOS/habitat/_common/fixtures/auth_user.json
HabitatOS/habitat/_common/locale/en/LC_MESSAGES/django.mo
HabitatOS/habitat/_common/locale/en/LC_MESSAGES/django.po
HabitatOS/habitat/_common/locale/pl/LC_MESSAGES/django.mo
HabitatOS/habitat/_common/locale/pl/LC_MESSAGES/django.po
HabitatOS/habitat/_common/management/__init__.py
HabitatOS/habitat/_common/management/commands/__init__.py
HabitatOS/habitat/_common/management/commands/i18n.py
HabitatOS/habitat/_common/management/commands/transifex.py
HabitatOS/habitat/_common/models/__init__.py
HabitatOS/habitat/_common/models/base.py
HabitatOS/habitat/_common/models/date.py
HabitatOS/habitat/_common/models/user.py
HabitatOS/habitat/_common/templates/admin/change_list_import_export.html
HabitatOS/habitat/biolab/.DS_Store
HabitatOS/habitat/biolab/__init__.py
HabitatOS/habitat/biolab/apps.py
HabitatOS/habitat/biolab/tests.py
HabitatOS/habitat/biolab/admin/__init__.py
HabitatOS/habitat/biolab/admin/experiment.py
HabitatOS/habitat/biolab/admin/observation.py
HabitatOS/habitat/biolab/admin/plant.py
HabitatOS/habitat/biolab/locale/en/LC_MESSAGES/django.mo
HabitatOS/habitat/biolab/locale/en/LC_MESSAGES/django.po
HabitatOS/habitat/biolab/locale/pl/LC_MESSAGES/django.mo
HabitatOS/habitat/biolab/locale/pl/LC_MESSAGES/django.po
HabitatOS/habitat/biolab/migrations/0001_initial.py
HabitatOS/habitat/biolab/migrations/__init__.py
