Metadata-Version: 1.1
Name: HabitatOS
Version: 0.9.0
Summary: Analog space habitat operating system.
Home-page: https://github.com/astromatt/HabitatOS
Author: Matt Harasymczuk
Author-email: HabitatOS@astrotech.io
License: MIT
Keywords: space exploration analog analogue habitat operating system
Platform: UNKNOWN
Classifier: Development Status :: 4 - Beta
Classifier: Intended Audience :: Science/Research
Classifier: Topic :: Scientific/Engineering
Classifier: Topic :: System :: Operating System
Classifier: License :: OSI Approved :: MIT License
Classifier: Programming Language :: Python :: 3.6
